tests/__init__.py
tests/test_functionality.py
tests/test_helper_functions.py
tests/test_students.py
battleships_pkg_epratt-1.0.0.dist-info/LICENSE
battleships_pkg_epratt-1.0.0.dist-info/METADATA
battleships_pkg_epratt-1.0.0.dist-info/WHEEL
battleships_pkg_epratt-1.0.0.dist-info/top_level.txt
battleships_pkg_epratt-1.0.0.dist-info/RECORD
