Metadata-Version: 2.1
Name: battleships-pkg-epratt
Version: 1.0.0
Summary: A battleships game built for the module ECM1400 at the University of Exeter.
Home-page: https://github.com/Edguardia/ECM1400-Battleships-Coursework
Author: Edward Pratt
Author-email: ep718@exeter.ac.uk
Classifier: Programming Language :: Python :: 3
Classifier: Operating System :: OS Independent
Classifier: License :: OSI Approved :: GNU General Public License v3 (GPLv3)
Requires-Python: >=3.11
License-File: LICENSE
